__init__.py
core.py
run.py
e/__init__.py
e/time test.py
p/__init__.py
p/beginnings.py
p/countdown.py
p/log.py
p/wf.py
p/y.py
p/yh.py
p/yz.py
ycc_test-5.0.dist-info/LICENSE
ycc_test-5.0.dist-info/METADATA
ycc_test-5.0.dist-info/WHEEL
ycc_test-5.0.dist-info/entry_points.txt
ycc_test-5.0.dist-info/top_level.txt
ycc_test-5.0.dist-info/RECORD
