Metadata-Version: 2.1
Name: ycc-test
Version: 5.0
Summary: 三圆计算器,cmd或shell(Terminal) sycc命令开始运行,ps:ycc是原版,sycc是因作者需要而定制版，不欢迎下载ycc-tset版本是测试上传版本
Home-page: http://pypi.org/project/ycc
Author: 神秘的·
Author-email: 3046479366@qq.com
License: MIT
Project-URL: pydroid(python for android仅限中国大陆使用, https://wws.lanzoui.com/iK2GFm24t3a
Project-URL: pydroid文件密码python, https://wws.lanzoux.com/iK2GFm24t3a
Keywords: ycc,3y,a_3y,Circle,圆,圆柱,圆环,py,Chinese,sycc,python,windows,Unix,linux,3,y,yc,yz
Platform: UNKNOWN
Classifier: Natural Language :: Chinese (Simplified)
Classifier: Development Status :: 6 - Mature
Classifier: Operating System :: Microsoft :: Windows
Classifier: Operating System :: POSIX :: Linux
Classifier: Operating System :: Unix
Classifier: Operating System :: iOS
Classifier: Operating System :: Android
Classifier: Operating System :: MacOS
Classifier: Topic :: Scientific/Engineering :: Mathematics
Classifier: Topic :: Terminals
Classifier: Topic :: System :: Shells
Classifier: License :: OSI Approved :: MIT License
Classifier: Programming Language :: Python :: 3
Classifier: Programming Language :: Python :: 3 :: Only
Classifier: Programming Language :: Python :: 3.6
Classifier: Programming Language :: Python :: 3.7
Classifier: Programming Language :: Python :: 3.8
Classifier: Programming Language :: Python :: 3.9
Classifier: Intended Audience :: Developers
Requires-Python: >=3.6
Requires-Dist: pdsystem (>=1.0.3)
